Metadata-Version: 2.1
Name: Cinemx
Version: 0.1
Summary: cine
Home-page: https://github.com/PachulinCool/cinemx
Author: pacheco
License: MIT
